README.rst
setup.py
src/nodeconductor_paas_oracle/__init__.py
src/nodeconductor_paas_oracle/admin.py
src/nodeconductor_paas_oracle/apps.py
src/nodeconductor_paas_oracle/backend.py
src/nodeconductor_paas_oracle/cost_tracking.py
src/nodeconductor_paas_oracle/extension.py
src/nodeconductor_paas_oracle/filters.py
src/nodeconductor_paas_oracle/log.py
src/nodeconductor_paas_oracle/models.py
src/nodeconductor_paas_oracle/perms.py
src/nodeconductor_paas_oracle/serializers.py
src/nodeconductor_paas_oracle/urls.py
src/nodeconductor_paas_oracle/views.py
src/nodeconductor_paas_oracle.egg-info/PKG-INFO
src/nodeconductor_paas_oracle.egg-info/SOURCES.txt
src/nodeconductor_paas_oracle.egg-info/dependency_links.txt
src/nodeconductor_paas_oracle.egg-info/entry_points.txt
src/nodeconductor_paas_oracle.egg-info/not-zip-safe
src/nodeconductor_paas_oracle.egg-info/requires.txt
src/nodeconductor_paas_oracle.egg-info/top_level.txt
src/nodeconductor_paas_oracle/migrations/0001_squashed_0007_change_support_requests.py
src/nodeconductor_paas_oracle/migrations/0002_ovm_iaas_support.py
src/nodeconductor_paas_oracle/migrations/0003_auto_20160808_0900.py
src/nodeconductor_paas_oracle/migrations/__init__.py