Metadata-Version: 1.1
Name: nodeconductor-paas-oracle
Version: 0.6.2
Summary: Plugin for custom Oracle PaaS solution.
Home-page: http://nodeconductor.com
Author: OpenNode Team
Author-email: info@opennodecloud.com
License: UNKNOWN
Platform: UNKNOWN
Classifier: Framework :: Django
Classifier: Intended Audience :: Developers
Classifier: Intended Audience :: System Administrators
Classifier: Operating System :: OS Independent
Classifier: License :: OSI Approved :: MIT License
